yara.cpython-38-x86_64-linux-gnu.so
ak_yara_python-3.11.0.dist-info/LICENSE
ak_yara_python-3.11.0.dist-info/RECORD
ak_yara_python-3.11.0.dist-info/WHEEL
ak_yara_python-3.11.0.dist-info/METADATA
ak_yara_python-3.11.0.dist-info/top_level.txt
