Metadata-Version: 2.1
Name: ak-yara-python
Version: 3.11.0
Summary: Python interface for YARA
Home-page: https://github.com/appknox/yara-python
Author: Victor M. Alvarez
Author-email: engineering@appknox.com
License: Apache 2.0
Platform: UNKNOWN
Classifier: Programming Language :: Python
Classifier: License :: OSI Approved :: Apache Software License
Classifier: Operating System :: OS Independent
Classifier: Development Status :: 5 - Production/Stable
